{
  "articleDate": "2026-07-02",
  "articleLink": "https://learngerman.dw.com/de/02072026-kurz-und-leicht-video-nachrichten-zum-deutschlernen/a-77801740",
  "articles": [
    {
      "title": "Anklage nach Explosionen an Nord-Stream-Pipelines",
      "text": "Die deutsche Bundesanwaltschaft hat einen Mann aus der Ukraine angeklagt. Sie glaubt, dass er den Anschlag auf die Nord-Stream-Gaspipelines in der Ostsee im Jahr 2022 geplant und organisiert hat. Explosionen haben damals die Pipelines stark beschädigt und sehr viel Methan freigesetzt. Der Mann sagt, dass er das nicht getan hat. Auch die Ukraine sagt, dass sie mit dem Anschlag nichts zu tun hat.\n\nBundesanwaltschaft (f., nur Singular) – eine staatliche Stelle (eine Behörde): sie untersucht für den Staat besonders schlimme oder wichtige Verbrechen und bringt Menschen vor Gericht\n\nAnschlag, Anschläge (m.)  –  hier: ein geplanter Angriff: man macht etwas kaputt\n\n",
      "vocab": [
        {
          "german": "jemanden an|klagen",
          "explanation": "jemanden für ein Verbrechen vor Gericht bringen; sagen, dass jemand etwas Verbotenes getan hat und versuchen, dass er dafür eine Strafe bekommt",
          "english": "accuse|accuse someone",
          "id": "1"
        },
        {
          "german": "Gaspipeline, -s (f., aus dem Englischen)",
          "explanation": "ein Rohr, durch das man eine Flüssigkeit von einem Ort zu einem anderen bringen kann, zum Beispiel flüssiges Gas",
          "english": "gas pipeline, -s (f., from English)",
          "id": "2"
        },
        {
          "german": "Explosion, -en (f.)",
          "explanation": "hier: eine Situation: etwas geht mit einem sehr lauten Geräusch plötzlich kaputt",
          "english": "explosion, -en (f.)",
          "id": "3"
        },
        {
          "german": "etwas beschädigen",
          "explanation": "etwas machen, so dass etwas nicht mehr gut funktioniert; etwas zum Teil kaputt machen",
          "english": "damage something",
          "id": "4"
        },
        {
          "german": "Methan frei|setzen",
          "explanation": "machen, dass das Gas Methan in die Umwelt kommt",
          "english": "release methane",
          "id": "5"
        }
      ]
    },
    {
      "title": "Russland greift Kyjiw an",
      "text": "Russland hat in der Nacht die ukrainische Hauptstadt Kyjiw wieder mit vielen Drohnen und Raketen angegriffen. Mindestens 13 Menschen sind gestorben und Dutzende verletzt. Russland hat gesagt, dass das eine Reaktion auf ukrainische Angriffe war. Die Ukraine hat in den letzten Wochen und Monaten verstärkt die russische Energieinfrastruktur und militärische Ziele angegriffen.\n\nRakete, -n (f.) – hier: ein schnelles Fluggerät: man benutzt es als Waffe in einem Krieg; es fliegt mit großer Kraft sehr weit und kann viel kaputt machen\n\n",
      "vocab": [
        {
          "german": "Drohne, -n (f.)",
          "explanation": "ein kleines Fluggerät: es kann selbständig über weite Strecken fliegen und man kann es als Waffe benutzen",
          "english": "drone, -n (f.)",
          "id": "6"
        },
        {
          "german": "etwas an|greifen",
          "explanation": "hier: eine militärische Aktion, um etwas kaputt zu machen (Substantiv: der Angriff)",
          "english": "to attack something",
          "id": "7"
        },
        {
          "german": "Dutzend, -e (n.)",
          "explanation": "im Singular: eine Gruppe von zwölf Dingen oder Personen; im Plural: eine große Anzahl",
          "english": "dozen, -e (n.)",
          "id": "8"
        },
        {
          "german": "Reaktion, -en (f.)",
          "explanation": "eine Aktion: jemand hat etwas gemacht und deshalb macht man auch etwas; eine Antwort durch Taten",
          "english": "reaction, -en (f.)",
          "id": "9"
        },
        {
          "german": "verstärkt",
          "explanation": "hier: stärker als vorher",
          "english": "reinforced",
          "id": "10"
        },
        {
          "german": "Energieinfrastruktur, -en (f., meist im Singular)",
          "explanation": "hier: wichtige Systeme und Dinge für den Alltag (z. B. Strom, Gas oder Wärme)",
          "english": "Energy infrastructure, -en (f., usually in the singular)",
          "id": "11"
        },
        {
          "german": "militärische Ziel, -e (n.)",
          "explanation": "hier: ein Ort des Militärs: dort arbeiten Soldaten und es gibt Waffen",
          "english": "military objective, -e (n.)",
          "id": "12"
        }
      ]
    },
    {
      "title": "Ärzte warnen vor Gesundheitskrise in Venezuela",
      "text": "Bei den zwei Erdbeben in Venezuela in der letzten Woche sind mindestens 2200 Menschen  gestorben, Zehntausende hat man noch nicht gefunden. Ärzte warnen jetzt vor einer Gesundheitskrise, weil sehr viele Menschen verletzt sind und es leicht zu Infektionen kommen kann. Außerdem war das venezolanische Gesundheitssystem schon vor den Erdbeben stark belastet.\n\n",
      "vocab": [
        {
          "german": "Erdbeben, - (n.)",
          "explanation": "ein Naturereignis oder eine Naturkatastrophe: die Erde bewegt sich",
          "english": "earthquake, - (n.)",
          "id": "13"
        },
        {
          "german": "vor etwas warnen",
          "explanation": "sagen, dass etwas Schlechtes passieren wird",
          "english": "warn about something",
          "id": "14"
        },
        {
          "german": "Gesundheitskrise, -n (f.)",
          "explanation": "eine schwierige Situation: es gibt Probleme in Krankenhäusern und mit Ärzten und Ärztinnen; kranke Menschen können nicht gut behandelt werden",
          "english": "health crisis, -n (f.)",
          "id": "15"
        },
        {
          "german": "Zehntausende",
          "explanation": "sehr viele; zwischen 20.000 und 90.000",
          "english": "Tens of thousands",
          "id": "16"
        },
        {
          "german": "Infektion, -en (f.)",
          "explanation": "die Tatsache, dass ein Mensch eine Krankheit bekommt",
          "english": "infection, -en (f.)",
          "id": "17"
        },
        {
          "german": "Gesundheitssystem, -e (n.)",
          "explanation": "alle medizinischen Personen und Organisationen in einem Land (z. B. Krankenhäuser, Ärzte und Ärztinnen)",
          "english": "health system, -e (n.)",
          "id": "18"
        },
        {
          "german": "stark belastet sein",
          "explanation": "hier: sehr viel Arbeit haben und viele Aufgaben nicht mehr schaffen",
          "english": "be heavily burdened",
          "id": "19"
        }
      ]
    }
  ]
}